gendiff/.DS_Store
gendiff/__init__.py
gendiff/cli.py
gendiff/diff.py
gendiff/file_parser.py
gendiff/formatters/__init__.py
gendiff/formatters/formatter.py
gendiff/formatters/json.py
gendiff/formatters/plain.py
gendiff/formatters/stylish.py
gendiff/scripts/__init__.py
gendiff/scripts/gendiff.py
gendiff/tests/.DS_Store
gendiff/tests/__init__.py
gendiff/tests/fixtures/file1.json
gendiff/tests/fixtures/file1.yaml
gendiff/tests/fixtures/file2.json
gendiff/tests/fixtures/file2.yaml
gendiff/tests/fixtures/plain_result.txt
gendiff/tests/fixtures/result1.txt
gendiff/tests/fixtures/stylish_result.txt
gendiff/tests/fixtures/tree_file_1.json
gendiff/tests/fixtures/tree_file_1.yml
gendiff/tests/fixtures/tree_file_2.json
gendiff/tests/fixtures/tree_file_2.yml
gendiff/tests/test_gendiff.py
gendiff/tree.py
mo_gendiff-1.0.0.dist-info/entry_points.txt
mo_gendiff-1.0.0.dist-info/WHEEL
mo_gendiff-1.0.0.dist-info/METADATA
mo_gendiff-1.0.0.dist-info/RECORD
